hdc/__init__.py
hdc/embeddings.py
hdc/functional.py
hdc/datasets/__init__.py
hdc/datasets/airfoil_self_noise.py
hdc/datasets/beijing_air_quality.py
hdc/datasets/emg_hand_gestures.py
hdc/datasets/european_languages.py
hdc/datasets/isolet.py
hdc/datasets/pamap.py
hdc/datasets/ucihar.py
hdc/datasets/utils.py
hdc-0.5.7.dist-info/LICENSE
hdc-0.5.7.dist-info/METADATA
hdc-0.5.7.dist-info/WHEEL
hdc-0.5.7.dist-info/top_level.txt
hdc-0.5.7.dist-info/RECORD
