Metadata-Version: 2.1
Name: hdc
Version: 0.5.7
Summary: Python library for Hyperdimensional Computing
Home-page: https://github.com/mikeheddes/hdc-lib
License: MIT
Project-URL: Source, https://github.com/mikeheddes/hdc-lib/
Project-URL: Documentation, https://mikeheddes.github.io/hdc-lib/
Platform: UNKNOWN
Requires-Python: >=3.6, <4
License-File: LICENSE
Requires-Dist: torch
Requires-Dist: pandas
Requires-Dist: requests
